SberQR/AsyncSberQR.py
SberQR/SberQr.py
SberQR/__init__.py
SberQR/api.py
SberQR/api_sync.py
SberQR/exceptions.py
SberQR/payload.py
SberQR/scope.py
SberQR/types.py
SberQR-2.0.0.dist-info/LICENSE
SberQR-2.0.0.dist-info/METADATA
SberQR-2.0.0.dist-info/WHEEL
SberQR-2.0.0.dist-info/top_level.txt
SberQR-2.0.0.dist-info/RECORD
