Metadata-Version: 2.1
Name: SberQR
Version: 2.0.0
Summary: Библиотека для работы с SberPay QR/Плати QR.
Home-page: https://github.com/bl4ckm45k/SberQR
Author: bl4ckm45k
Author-email: nonpowa@gmail.com
License: MIT
Classifier: Programming Language :: Python :: 3.7
Classifier: Programming Language :: Python :: 3.8
Classifier: Programming Language :: Python :: 3.9
Classifier: Programming Language :: Python :: 3.10
Classifier: Programming Language :: Python :: 3.11
Classifier: Framework :: AsyncIO
Classifier: Intended Audience :: Developers
Classifier: License :: OSI Approved :: MIT License
Classifier: Operating System :: OS Independent
Classifier: Topic :: Office/Business :: Financial
Requires-Python: >=3.7
License-File: LICENSE
Requires-Dist: aiohttp >=3.8.4
Requires-Dist: certifi >=2023.11.17
Requires-Dist: ujson >=5.9.0
Requires-Dist: pytz ==2022.1
Requires-Dist: qrcode[pil] >=7.3.1
Requires-Dist: redis >=4.2.0rc1
Requires-Dist: urllib3 ~=2.0.3
